[
    {
        "category": "Introduction",
        "categoryHref":"/index.html",
        "sections":
        [
            {
                "sectionName":"",
                "pages":
                [
                    {"pageName": "Introduction", "href":"/index.html"},
                    {"pageName": "Why is This Important?", "href":"/WhyIsThisImportant.html"},
                    {"pageName": "What is the Approach?", "href":"/WhatIsTheApproach.html"}
                ]
            }
        ]
    },
    {
        "category": "Methods",
        "categoryHref": "/Methods.html",
        "sections":
        [
            {
                "sectionName":"",
                "pages":
                [
                    { "pageName": "Inclusive Learning", "href": "/InclusiveLearning.html" },
                    { "pageName": "Accessibility Principles", "href": "/AccessibilityPrinciples.html"},
                    { "pageName": "Techniques", "href": "/Techniques.html"},
                    { "pageName": "Metadata", "href": "/Metadata.html"},
                    { "pageName": "Learner Needs and Preferences", "href": "/LearnerNeedsAndPreferences.html"},
                    { "pageName": "Video Content and Learning", "href": "/VideoContentAndLearning.html"},
                    { "pageName": "Audio Content and Learning", "href": "/AudioContentAndLearning.html"},
                    { "pageName": "Authoring of Content", "href": "/AuthoringContent.html"},
                    { "pageName": "Cognitive Considerations", "href": "/CognitiveConsiderations.html"}
                ]
            }
        ]
    }
]
